dirstree/__init__.py
dirstree/py.typed
dirstree/crawlers/__init__.py
dirstree/crawlers/abstract.py
dirstree/crawlers/crawler.py
dirstree/crawlers/group.py
dirstree/crawlers/python_crawler.py
dirstree-0.0.3.dist-info/LICENSE
dirstree-0.0.3.dist-info/METADATA
dirstree-0.0.3.dist-info/WHEEL
dirstree-0.0.3.dist-info/top_level.txt
dirstree-0.0.3.dist-info/RECORD
